fzpcb/__init__.py
fzpcb/array_2d.py
fzpcb/board.py
fzpcb/breadboard_svg.py
fzpcb/cell.py
fzpcb/colour_list.py
fzpcb/coords.py
fzpcb/defaults.yaml
fzpcb/element.py
fzpcb/fzp_xml.py
fzpcb/fzpcb.py
fzpcb/grid_drawing.py
fzpcb/helpers.py
fzpcb/layout.py
fzpcb/parse_yaml.py
fzpcb/pcb_shape_mixin.py
fzpcb/pcb_svg.py
fzpcb/schematic_svg.py
fzpcb-0.0.3.dist-info/licenses/LICENSE.txt
fzpcb-0.0.3.dist-info/METADATA
fzpcb-0.0.3.dist-info/WHEEL
fzpcb-0.0.3.dist-info/entry_points.txt
fzpcb-0.0.3.dist-info/top_level.txt
fzpcb-0.0.3.dist-info/RECORD
