Metadata-Version: 2.4
Name: fzpcb
Version: 0.0.3
Author-email: Philip Tregoning <Philip.Tregoning@gmail.com>
Project-URL: Documentation, https://github.com/Twirlip-of-the-Mists/fzpcb#readme
Project-URL: Issues, https://github.com/Twirlip-of-the-Mists/fzpcb/issues
Project-URL: Source, https://github.com/Twirlip-of-the-Mists/fzpcb
Classifier: Development Status :: 4 - Beta
Classifier: Programming Language :: Python
Classifier: Programming Language :: Python :: 3.9
Requires-Python: >=3.9
License-File: LICENSE.txt
Requires-Dist: pyyaml
Requires-Dist: click
Requires-Dist: colour
Requires-Dist: svgwrite
Dynamic: license-file
